[
  {
    "full_name": "corda/corda",
    "stargazers_count": 3620,
    "open_issues_count": 224,
    "forks_count": 996
  },
  {
    "full_name": "openmrs/openmrs-core",
    "stargazers_count": 1011,
    "open_issues_count": 171,
    "forks_count": 2860
  },
  {
    "full_name": "openmrs/openmrs-core",
    "stargazers_count": 1011,
    "open_issues_count": 171,
    "forks_count": 2860
  },
  {
    "full_name": "idanceinbetween/gluck-ui",
    "stargazers_count": 0,
    "open_issues_count": 1,
    "forks_count": 0
  }
]